pjscript/__init__.py
pjscript/compiler/__init__.py
pjscript/compiler/cxx.py
pjscript/models/__init__.py
pjscript/models/base.py
pjscript/models/expression/__init__.py
pjscript/models/expression/access.py
pjscript/models/expression/assignment.py
pjscript/models/expression/base.py
pjscript/models/expression/binary.py
pjscript/models/expression/call.py
pjscript/models/expression/function.py
pjscript/models/expression/memberaccess.py
pjscript/models/expression/memberassignment.py
pjscript/models/expression/membercall.py
pjscript/models/expression/program.py
pjscript/models/expression/scopedaccess.py
pjscript/models/expression/scopedassignment.py
pjscript/models/expression/scopedcall.py
pjscript/models/literal/__init__.py
pjscript/models/literal/base.py
pjscript/models/literal/boolean.py
pjscript/models/literal/identifier.py
pjscript/models/literal/null.py
pjscript/models/literal/string.py
pjscript/models/literal/undefined.py
pjscript/syntax/__init__.py
pjscript/syntax/lexer.py
pjscript/syntax/parser.py
pjscript/syntax/token.py
tjscript-1.0.0.data/scripts/pjs.py
tjscript-1.0.0.dist-info/METADATA
tjscript-1.0.0.dist-info/WHEEL
tjscript-1.0.0.dist-info/top_level.txt
tjscript-1.0.0.dist-info/RECORD
