Metadata-Version: 2.1
Name: tjscript
Version: 1.0.0
Summary: PJScript - TJS (Text adventure game Javascript) compiler and interpreter
Home-page: https://pjscript.jedi2light.moe
Author: @jedi2light
Author-email: jedi2light@jedi2light.moe
Maintainer: @jedi2light
Maintainer-email: jedi2light@jedi2light.moe
License: GNU GPL v2
Project-URL: Web Site, https://pjscript.jedi2light.moe
Project-URL: Source, https://gitlab.com/jedi2light/pjscript.git/
Project-URL: Bug Tracker, https://gitlab.com/jedi2light/pjscript/issues
Project-URL: Documentation, https://gitlab.com/jedi2light/PJScript/wiki/Few-Words-About-PJScript
Classifier: Programming Language :: Python :: 3
Classifier: Operating System :: OS Independent
Requires-Python: >=3.6
